{"title": "Интересное предложение", "rating": "4.4", "phone": "tel:+73466650160", "address": "Ханты-Мансийский автономный округ,  Нижневартовск,  улица noindexМира/noindex,  3", "lonlat": ["76.551158999999998", "60.945374999999999"], "work_time": "Время работыкруглосуточноКруглосуточно ", "price": 0, "price_list": [], "stuff_list": [], "site": "http://zoon.ru/redirect/?to=http%3A%2F%2Finfiniti-spa.ru&hash=b13e7fbff4ded933387231255695e62a&from=5b30b0faaa136a373366e81d.57ff&ext_site=ext_site&backurl=https%3A%2F%2Fnizhnevartovsk.zoon.ru%2Fbeauty%2Fmuzhskoj_spa-salon_infiniti_na_ulitse_mira_3%2F", "reviews": [], "images": [], "promos": [{"title": "Акция в спа-салоне Инфинити", "tag": "Специальная акция", "card": "Постоянная акция"}], "tags": ["Салоны красоты и СПА"], "witget": "no"}