{"title": "Прайс-лист студии красоты и здоровья MrBrovkin на Киевской улице", "rating": "4.8", "phone": "tel:+79087779046", "address": "Иркутск,  noindexКиевская/noindex улица,  2, 214 офис; 2 этаж", "lonlat": ["104.28594199999996", "52.282414999999283"], "work_time": "Время работыкруглосуточнопо предварительной записи: пн-вс ", "price": 0, "price_list": [{"name": "Татуаж бровей", "min-price": "4000", "max-price": "—8000"}, {"name": "Массаж лица", "min-price": " ≈ 500", "max-price": " "}, {"name": "Массаж спины", "min-price": " ≈ 850", "max-price": " "}, {"name": "Пирсинг ушей", "min-price": "400", "max-price": "—500"}, {"name": "Удаление тату", "min-price": " ≈ 1000", "max-price": " "}], "stuff_list": [], "site": "http://zoon.ru/redirect/?to=http%3A%2F%2Fmrbrovkin.ru%2F&hash=29c5b7ba6258ca5eeb54147216d3c2c2&from=58e2464340c08886708d5ff4.5d4f&ext_site=ext_site&backurl=https%3A%2F%2Firkutsk.zoon.ru%2Fbeauty%2Fstudiya_krasoty_i_zdorovya_mrbrovkin_na_kievskoj_ulitse%2F", "reviews": [{"rating": " ", "name": "Эвелина Барановская", "comment": "Сразись со мной в битве интеллектов в игре «Слово за слово»!"}, {"rating": " ", "name": "Радий Бровкин", "comment": "Лазерный карбоновый пилинг лица в Иркутске. Запись по т. +7 (908) 777-90-46"}, {"rating": " ", "name": "Радий Бровкин", "comment": "ТАТУ по эскизам на любой вкус. Запись по т. +7 (908) 777-90-46"}, {"rating": " ", "name": "Радий Бровкин", "comment": "ТАТУ по эскизам на любой вкус. Запись по т. +7 (908) 777-90-46"}], "images": ["https://p0.zoon.ru/preview/NGlQc2wOPJ7PVFk9FY_rGw/800x365x85/1/f/c/original_58e2464340c08886708d5ff5_5e4ce3b4acd08.jpg", "https://p0.zoon.ru/preview/Hzxej7I55Mn2F-Sjb7uT_g/800x449x85/1/f/4/original_58e2464340c08886708d5ff5_5e4ce0a730fe2.jpg", "https://p0.zoon.ru/preview/VxK0-BTtjIllhHfIdg9z3g/800x329x85/1/f/9/original_58e2464340c08886708d5ff5_5e4cf20339f13.jpg"], "promos": [], "tags": ["Салоны красоты и СПА"], "witget": "no"}