{"title": "Похожие салоны красоты и спа поблизости", "rating": " ", "phone": "tel:+78352375005", "address": "Чувашская Республика,  Чебоксары,  noindexМосковский/noindex проспект,  23к2", "lonlat": ["47.212162999999997", "56.144291000000003"], "work_time": "Время работыежедневно: 09:00 - 21:00 ", "price": "очень высокая", "price_list": [], "stuff_list": [], "site": "http://zoon.ru/redirect/?to=https%3A%2F%2Fwww.medusanail.ru&hash=5e28af4f01e0dd61dd1667f85cedbb8b&from=5e7c23a5615a894d780350b2.ced3&ext_site=ext_site&backurl=https%3A%2F%2Fcheboksary.zoon.ru%2Fbeauty%2Fstudiya_nogtevogo_dizajna_i_krasoty_medusa_na_moskovskom_prospekte%2F", "reviews": [], "images": [], "promos": [], "tags": ["Салоны красоты и СПА"], "witget": "no"}