{"title": "Похожие салоны красоты и спа поблизости", "rating": "4.8", "phone": "tel:+79006906519", "address": "Брянск,  улица noindexУльянова/noindex,  2", "lonlat": ["34.310344000000001", "53.299723"], "work_time": "Время работыежедневно: 10:00 - 19:00 ", "price": 0, "price_list": [], "stuff_list": [], "site": "http://zoon.ru/redirect/?to=https%3A%2F%2Fwww.instagram.com%2Fsalon32gil&hash=ca8e29e7cd530d41ed9f2b5b44978371&from=5cb3fb053bc06c8b6172ec78.4cab&ext_site=ext_instagram&backurl=https%3A%2F%2Fbryansk.zoon.ru%2Fbeauty%2Fparikmaherskaya_ekonomka%2F", "reviews": [{"rating": "5", "name": " ", "comment": "Приходила делать прическу на выпускной, обслуживание прекрасное, осталась довольна, а самое главное по минимальным ценам, советую и ставлю 5/5"}], "images": ["https://p1.zoon.ru/preview/1M8j1GGZ37RMA2rk-ObfEA/450x600x85/1/7/0/original_5cb3fb053bc06c8b6172ec7c_5d0cac79addae.jpg"], "promos": [], "tags": ["Салоны красоты и СПА"], "witget": "no"}