{"title": "Салон тату Оберег ", "rating": "4", "phone": "tel:+79025696466", "address": "Братск, Обручева, 22, 1002 офис", "lonlat": ["101.628424", "56.158583999999998"], "work_time": " ", "price": 0, "price_list": [], "stuff_list": [], "site": "http://zoon.ru/redirect/?to=https%3A%2F%2Fvk.com%2Fid388030268&hash=682061a634e08b23f976263effa9af9c&from=5aa418f4a24fd9153980971e.d88d&ext_site=ext_vk&backurl=https%3A%2F%2Fbratsk.zoon.ru%2Fbeauty%2Fsalon_tatu_obereg%2Freviews%2F", "reviews": [{"rating": " ", "name": "Антонина", "comment": "точно такая во сколько обойдётся? и сколько сеансов?"}, {"rating": " ", "name": "Данил Мирный", "comment": "Владимир! Только что я узнал кто тебя любит. Не знаю, знаешь ли ты, но это… Полная информаця по ссылке :"}, {"rating": " ", "name": "Татьяна Трушина", "comment": "Ваван, все твои тайны раскрыты здесь //"}, {"rating": " ", "name": "Тонечка Журавлёва", "comment": "С Днем рождения! Счастья тебе и творческих успехов. Пусть муза никогда тебя не покидает. Продолжай творить красоту"}, {"rating": " ", "name": "Владимир Радаев", "comment": "Марина Ускова (28.09.2018):Внимание!!! «Трезвые дворы Братск» аферисты чистой воды!!! Михаил Горбик и Валентин Усманов люди которые сами употребляют алкоголь и бывшие наркоманы! Я предложила пройти им полиграф, что бы вывести их на чистую воду, но они не согласились! Семьи у обоих пьющие как мы видим под фото ниже! Проект создали для самапиара и вымогательста денежных средств у населения нашего города! На связь теперь они не выходят, просто игнорируют! Всех граждан пострадавших от этих «чмооператоров» просьба связаться со мной, так ка… — Читать дальшек уже 5 человек написали заявление на их неправомерные действия! Всех к кого они будут в будущем снимать звоните мне +7 (902) 569-64-66, особенно если Свами Несовершеннолетнии дети!!! Готова оказать безвозмездную помощь всем пострадавшим!!! Рейпост друзья!!! "}, {"rating": " ", "name": "Владимир Радаев", "comment": "Архив эскизов для тату. (11.08.2018):"}, {"rating": " ", "name": "Владимир Радаев", "comment": "Идеи татуировок (06.08.2018):Украшение на красивые спинки"}], "images": [], "promos": [], "tags": ["Салоны красоты и СПА"], "witget": "no"}