{"title": "Похожие салоны красоты и спа поблизости", "rating": "3", "phone": "tel:+79821929250", "address": "Ханты-Мансийский автономный округ,  Сургут,  улица noindexОстровского/noindex,  29А, 3 этаж", "lonlat": ["73.399508999999995", "61.265875000000001"], "work_time": " ", "price": 0, "price_list": [], "stuff_list": [], "site": "http://zoon.ru/redirect/?to=https%3A%2F%2Fwww.instagram.com%2Fdorogoy.ya.perezvonyu_sgt&hash=eeba3f53e82d05bea03324a360b0e5bb&from=5ce3b75b92128cbc9d74855f.6063&ext_site=ext_instagram&backurl=https%3A%2F%2Fsurgut.zoon.ru%2Fbeauty%2Fsalon_krasoty_dorogoj_ya_perezvonyu_na_ulitse_ostrovskogo%2F", "reviews": [], "images": [], "promos": [], "tags": ["Салоны красоты и СПА"], "witget": "no"}