{"title": "Похожие салоны красоты и спа поблизости", "rating": "4.5", "phone": "tel:+79048799200", "address": "Ханты-Мансийский автономный округ, Сургут, Быстринская, 8, 103 офис; 10 этаж", "lonlat": ["73.426372999999998", "61.260719999999999"], "work_time": "Время работыПн-Сб: 10:00—20:00по предварительной записи: пн-сб ", "price": 0, "price_list": [], "stuff_list": [], "site": "http://zoon.ru/redirect/?to=https%3A%2F%2Fwww.instagram.com%2Felenakhamitova.surgut&hash=91053836b7d24b17cad951cf9bcb1b4f&from=5555cc9040c0881c758c994b.7439&ext_site=ext_instagram&backurl=https%3A%2F%2Fsurgut.zoon.ru%2Fbeauty%2Fmasterskaya_krasoty_ptichki%2F", "reviews": [{"rating": " ", "name": "Денис Екимов", "comment": "Проверенный временем недорогой салон"}], "images": [], "promos": [], "tags": ["Салоны красоты и СПА"], "witget": "no"}