{"title": "Студия причесок Саша на улице Конева", "rating": "3.8", "phone": "tel:+79215316409", "address": "Вологда, Конева, 33, 1 этаж", "lonlat": ["39.900686", "59.186324999999997"], "work_time": "Время работыПн-Сб: 10:00—20:00; Вс: 10:00—18:00 ", "price": 0, "price_list": [], "stuff_list": [], "site": "http://zoon.ru/redirect/?to=https%3A%2F%2Fvk.com%2Fid190833334&hash=98010042d2ad23d5cee844c813545e9c&from=5555d7bc40c0881c758d0b71.525c&ext_site=ext_vk&backurl=https%3A%2F%2Fvologda.zoon.ru%2Fbeauty%2Fstudiya_prichesok_sasha_na_ulitse_koneva%2Freviews%2F", "reviews": [{"rating": " ", "name": "Анонимный пользователь", "comment": "Можно сделать глазирование волос?Если да то за сколько?"}, {"rating": " ", "name": "Людмила", "comment": "Скажите а вы делаете наращивания ногтей? сколько стоит?,и когда можно записаться?,какой стаж у мастера?"}, {"rating": " ", "name": "Аня Захарова", "comment": "Здравствуйте, а сколько будет стоить механическая чистка лица?"}, {"rating": " ", "name": " ", "comment": "ответили"}, {"rating": " ", "name": "Татьяна Бабушкина", "comment": "сколько стоит прокол ушей и со скольки прокалываете"}, {"rating": " ", "name": "Арина Солдатова", "comment": "Современная официальная медицина."}, {"rating": " ", "name": "Арина Солдатова", "comment": "Ирина, но ведь современная медицина не рекомендует прокалывать ушки до 3х лет"}, {"rating": " ", "name": " ", "comment": "Система с 75 более современный метод, безболезненный, бесшумный, прокалывают круглый год)"}, {"rating": " ", "name": "Оксана Гузанова", "comment": "Ирина, тот же вопрос.И в какое время года их лучше прокалывать?"}, {"rating": " ", "name": "Тоня Фомичева", "comment": "Ирина, а это больно и быстро ли заживают ушки?"}, {"rating": " ", "name": " ", "comment": "Прокол ушей пистолетом с сережками -600 руб, прокол системой с 75 -500 руб+ стоимость сережек цены от 550 и выше, запись по т или в лс, прокалываем с 7 месяцев рекомендуем с годика"}, {"rating": " ", "name": "Елена Пушина", "comment": "Тот же вопрос?"}, {"rating": " ", "name": "Наталия Макарова", "comment": "А мне всет не ответили"}, {"rating": " ", "name": "Юлечка Ромина", "comment": "Косметолог, мне тоже ответ!"}, {"rating": " ", "name": " ", "comment": "Ответили"}, {"rating": " ", "name": "Вика Коткова", "comment": "тоже интересно…"}, {"rating": " ", "name": " ", "comment": "ответили"}, {"rating": " ", "name": "Анютка Винцкевич", "comment": "стоимость наращивания"}, {"rating": " ", "name": "Ксения Солодягина", "comment": "Подскажите стоимость прокола ушей?"}, {"rating": " ", "name": " ", "comment": "ответила"}, {"rating": " ", "name": "Валя Овчинникова", "comment": "Можно мне тоже стоимость?"}, {"rating": " ", "name": " ", "comment": "ответила"}, {"rating": " ", "name": "Алла Малафеевская", "comment": "И мне)"}, {"rating": " ", "name": " ", "comment": "ответила"}, {"rating": " ", "name": "Екатерина Евгеньевна", "comment": "Ирина, можно тоже узнать стоимость?"}, {"rating": " ", "name": " ", "comment": "Ответила"}, {"rating": " ", "name": " ", "comment": "Ответила"}, {"rating": " ", "name": "Ирина Котова", "comment": "Какая цена прокола ушей?"}, {"rating": " ", "name": "Михаил-Чижов-И Валентина-Роздухова", "comment": "Ирина, подскажите стоимость ламинирования ресничек."}, {"rating": " ", "name": "Настёна Власова", "comment": "Девочки,добрый день.Подскажите по цене био татуаж бровей и можно ли на завтра записаться?"}, {"rating": " ", "name": "Людмилка Ерёмина", "comment": "здравствуйте,скажите режим работы.можно в личку."}, {"rating": " ", "name": " ", "comment": "Ответила"}, {"rating": " ", "name": "Лариса Катаева", "comment": "Пилинг"}, {"rating": " ", "name": " ", "comment": "ответила"}, {"rating": " ", "name": "Лариса Катаева", "comment": "Сколько стоит мезотерапия и митинг?"}, {"rating": " ", "name": "Оксана Данилова", "comment": "Здравствуйте, подскажите сколько стоит прокол ушей и с какого возраста"}, {"rating": " ", "name": " ", "comment": "ответила"}, {"rating": " ", "name": "Наташа Савина", "comment": "Косметолог-визажист. Макияж., одно ушко 550?"}, {"rating": " ", "name": " ", "comment": "Прокалываем и до года, но рекомендуем с годика"}, {"rating": " ", "name": "Инна Андреевна", "comment": "Здравствуйте с какого возраста?"}, {"rating": " ", "name": "Евгения Коноплёва", "comment": "Здравствуйте. Подскажите,а можно прийти со своими сережками?"}, {"rating": " ", "name": " ", "comment": "запись по т"}, {"rating": " ", "name": " ", "comment": "Прокол ушей пистолетом + сережки — 550 руб, прокол системой с 75 — прокол 500 + сережки цены от 550 и выше"}, {"rating": " ", "name": "Наталья Савенкова", "comment": "И мне"}, {"rating": " ", "name": "Дилшода Наимова", "comment": "И мне"}, {"rating": " ", "name": "Ирина Котова", "comment": "И мне пож."}, {"rating": " ", "name": "Ольга Яшина", "comment": "И мне подскажите, сколько стоит прокол и со скольки лет?"}, {"rating": " ", "name": " ", "comment": "ответила"}, {"rating": " ", "name": "Таня Хабалева", "comment": "Здравствуйте! На ламинирование ресниц, на следущей неделе есть запись?"}, {"rating": " ", "name": "Светлана Вологодская", "comment": "Косметолог-визажист. Макияж., здравствуйте,подскажите сколько держится?"}, {"rating": " ", "name": " ", "comment": "Ламинирование ресниц стоит -1300 руб. запись по т или в личное сообщение"}, {"rating": " ", "name": "Ольга Пьянкова", "comment": "Косметолог-визажист. Макияж., стоимость ламинирования?"}, {"rating": " ", "name": " ", "comment": "ответила"}, {"rating": " ", "name": "Наталья Найченко", "comment": "Косметолог-визажист. Макияж., и мне пож скажите и стоимость?"}, {"rating": " ", "name": " ", "comment": "ответила"}, {"rating": " ", "name": "Татьяна Параничева", "comment": "Добрый вечер. Завтра днём есть свободное время: на массаж лица и наращивание ресниц?"}, {"rating": " ", "name": " ", "comment": "смывка - 200, наращивание простой объем- 750, двойной -950, запись по т"}, {"rating": " ", "name": "Юлия Крашенинина", "comment": "Ирина, а сколько стоит снятие ресниц от другого мастера и наращивание новых??"}, {"rating": " ", "name": " ", "comment": "Татьяна,здравствуйте,как вам в 12.00?"}, {"rating": " ", "name": "Саша Конева", "comment": "А у нас появилась новая ухаживающая процедура Коллагирование волос живым коллагеном — это восстановление волос на молекулярном уровне. ⠀ Восстановление коллагеном подходит: тем, у кого пушатся или вьются волосы, а также обладательницам ломких, пересушенных, обесцвеченных волос. ВООБЩЕМ ОН ПОДХОДИТ ВСЕМ ⠀ Что же такое Коллаген — это белок, наличие которого организму жизненно необходимо. Он выполняет множество функций, отвечает за красоту прически, ногтей, кожи. Из-за воздействия ультрафиолетовых лучей, химических составов, курения,… — Читать дальше алкоголя, стрессов организм может утрачивать столь важный элемент. Все отражается на состоянии здоровья, внешнем виде. ⠀ Нехватка белка в волосах ведет к тому, что они становятся тусклыми, ломкими, безжизненными. И-и-и мы это все исправляем нашим уходом с коллагеном Стоимость 1000 руб ‼# СТУДИЯ ПРИЧЕСОК САША "}, {"rating": " ", "name": "Саша Конева", "comment": "airtouch — идеальная техника окрашивания в период вируса От 3х до 6 месяцев ты будешь выглядеть потрясающе без посещения своего колориста Главное правильно поддерживать цвет и состояние волос дома. Об этом я тебе расскажу во время окрашивания Получилось очень естественно и натурально ‼Формула тонирования‼ N\\36+N\\75 # СТУДИЯ ПРИЧЕСОК САША"}, {"rating": " ", "name": "Саша Конева", "comment": "Кератиновое выпрямление волос — мифы и реальность Кератиновое выпрямление от 1500р (далее зависит от длины и густоты ваших волос) Милые дамы, которые о кератине не знают или хотят знать больше.Сейчас я постараюсь раскрыть все вопросы, которые обычно возникают. Всё нижеизложенное – на основании моего опыта использования кератина – прежде всего на себе. Но также я учитываю опыт своих подруг и просто знакомых. И ещё – ни в коем случае не ставлю перед собой задачу переубедить тех, чья позиция «не пробовал, но осуждаю». Мы здесь все взросл… — Читать дальшеые люди, и каждый волен делать с собой, что хочет. Или не делать. Итак… Миф 1. «Кератин портит волосы» Да, бывают случаи, когда после процедуры выпрямления волосы у девушек портились, но дело не в том, что процедура в принципе вредна. Испортиться волосы могут по двум причинам. Во-первых, если мастер пожалел состав при этом нарушая технологию и начал работать утюжком. Естественно, после этого волосы будут сожженными – они же не были защищены кератином, а при такой высокой температуре, какая требуется для процедуры, у волос просто не остаётся шансов. Во-вторых, если использовали дешевый/сомнительный состав. Хороший состав не может стоить копейки! Вам повезёт, если химоза по цене «рупь за ведро» вам не навредит – ни волосам, ни здоровью в целом. Считайте тогда, что дешево отделались. Такие составы используют только те, кто берёт не качеством, а количеством. Этим людям не важно, будет ли доволен клиент, придёт ли он ещё. Не придёт, да это и не важно. Всегда найдётся сотня новых, которые захотят за копейки стать принцессами. Миф 2. «Если перестать делать кератин, волосы станут хуже» За редким исключением, у девушек, которые делают кератин, волосы изначально пористые, пушистые, сами по себе не блестят, форма не пойми какая. Потом они делают кератин и волосы становятся гладкими, блестящими, как с обложки журнала. А потом девушка по каким-то причинам хочет вернуться к кудрям. И тут начинаются «странные» превращения. Волосы становятся пористыми, пушистыми, форма не пойми какая… К хорошему быстро привыкаешь. Почему-то у некоторых начинаются провалы в памяти, и они напрочь забывают, какими были их волосы до кератина. А ведь точно такими же, какими стали после! Сознание просто отказывается воспринимать реальность. Кератин – не волшебная таблетка, которую раз принял, и на всю жизнь изменился. Красоту волос надо поддерживать.(Буссульфатные шампуни и бальзамы ОДНОЙ МАРКИ и увлажнение такое как маски 1—2 раза в неделю, масло для волос и сыворотки) Это как умываться – невозможно умыться впрок, на всю жизнь чистым не станешь. Моя знакомая, которая сделала кератин, чтобы избавиться от эффекта пушистости, а потом решила дождаться, когда он весь смоется, чтобы попробовать другой состав и решить для себя, какой для неё лучше, в этом плане оказалась очень объективной. Вернулась пушистость, волосы стали тонкими, как и были ДО. Она просто помнила это ощущение. Некоторые категорически не хотят помнить. Миф 3. «Нужно использовать только фирменные шампуни, а это дорого и неудобно!» Конечно, производители кератина хотят заработать на дополнительных товарах, это вполне нормально. Но дело в том, что волосам не важно, каким шампунем их моют, – за 2000 или за 500 руб. Главное, чтобы шампунь был без сульфатов. Миф 4. «Выпрямление держится 6 месяцев» Держится. В сказках и мечтах. А ещё через полтора-два года регулярных процедур. Когда мастер обещает «4—6 месяцев» с первого раза – заманивает и нагло врёт. Первый раз выпрямление продержится два-три месяца. Потом появятся объём и волна. Блеск продержится существенно дольше, это да. Но чудес ждать не нужно. Кератин вымывается постепенно, поэтому вы в одночасье не проснётесь кудрявой, как раньше. Но, тем не менее, эффект будет уже не тот. Поделись постом на своей странице, ведь именно сейчас твоя подруга сомневается или ищет информацию и мастера, чтобы сделать свои волосы прекрасными!# СТУДИЯ ПРИЧЕСОК САША "}], "images": [], "promos": [], "tags": ["Салоны красоты и СПА"], "witget": "no"}