{"title": "Другие салоны красоты и спа, которые мы рекомендуем", "rating": "3", "phone": "tel:+79248774727", "address": "Республика Саха (Якутия),  Якутск,  noindexГорького/noindex,  100, 1 этаж; вход со двора", "lonlat": ["129.71436199999999", "62.030228999999999"], "work_time": "Время работыВт-Вс: 10:00—19:00 ", "price": 0, "price_list": [], "stuff_list": [], "site": "http://zoon.ru/redirect/?to=https%3A%2F%2Fwww.instagram.com%2Fmaster_studio_ykt&hash=e6ef6cd6ad32b0f80a9e5f8d71dc7ae1&from=55549a1140c08864448b5a84.69c1&ext_site=ext_instagram&backurl=https%3A%2F%2Fyakutsk.zoon.ru%2Fbeauty%2Fparikmaherskaya_master%2F", "reviews": [{"rating": " ", "name": "Миисэ Semenov", "comment": "Хороший мастер, и цена приемлемая"}], "images": [], "promos": [], "tags": ["Салоны красоты и СПА"], "witget": "no"}