{"title": "Салон красоты City Nails на проспекте Вернадского", "rating": "3.3", "phone": "tel:+74996861866", "address": "Москва, проспект Вернадского, 105к4", "metro": ["Юго-Западная 0.2 км"], "rayons": ["Округ ЗАО", "Район Тропарёво-Никулино"], "lonlat": ["37.486445000000003", "55.663857"], "work_time": "Время работыежедневно: 10:00 - 22:00 ", "price": 0, "price_list": [{"name": "Шугаринг", "min-price": "250", "max-price": "—1190"}], "stuff_list": [], "site": "http://zoon.ru/redirect/?to=http%3A%2F%2Fcitynails.studio%2F&hash=1ac79409945363de933e2b2bc2b49db1&from=5be3c67acd02a74b0568873b.3c01&ext_site=ext_site&backurl=https%3A%2F%2Fzoon.ru%2Fmsk%2Fbeauty%2Fsalon_krasoty_city_nails_na_prospekte_vernadskogo%2Freviews%2F", "its route": "Yes", "social_links": ["citynails.studio/ http://zoon.ru/redirect/?to=http%3A%2F%2Fcitynails.studio%2F&hash=1ac79409945363de933e2b2bc2b49db1&from=5be3c67acd02a74b0568873b.3c01&ext_site=ext_site&backurl=https%3A%2F%2Fzoon.ru%2Fmsk%2Fbeauty%2Fsalon_krasoty_city_nails_na_prospekte_vernadskogo%2Freviews%2F", "ВКонтакте http://zoon.ru/redirect/?to=https%3A%2F%2Fvk.com%2Fcitynails_moscow&hash=ff2233c6f40e748b1ca0ebab742db2b7&from=5be3c67acd02a74b0568873b.3c01&ext_site=ext_vk&backurl=https%3A%2F%2Fzoon.ru%2Fmsk%2Fbeauty%2Fsalon_krasoty_city_nails_na_prospekte_vernadskogo%2Freviews%2F", "Facebook http://zoon.ru/redirect/?to=https%3A%2F%2Fwww.facebook.com%2Fcitynails.moscow&hash=5cd856ea8e9db935ec9f758a4c5225cc&from=5be3c67acd02a74b0568873b.3c01&ext_site=ext_facebook&backurl=https%3A%2F%2Fzoon.ru%2Fmsk%2Fbeauty%2Fsalon_krasoty_city_nails_na_prospekte_vernadskogo%2Freviews%2F", "Instagram http://zoon.ru/redirect/?to=https%3A%2F%2Fwww.instagram.com%2Fcitynails_moscow&hash=9a4a7e269e492c162cf38fc3aab0dabe&from=5be3c67acd02a74b0568873b.3c01&ext_site=ext_instagram&backurl=https%3A%2F%2Fzoon.ru%2Fmsk%2Fbeauty%2Fsalon_krasoty_city_nails_na_prospekte_vernadskogo%2Freviews%2F"], "reviews": [{"rating": "5", "name": "Настя", "comment": "Хочу в студию на Югозападной часто. Очень мне нравится. Мастеров меняю. Была у Риммы. НОНЫ, Чинары, Рузанны. Делают они любой вид маника, дизайны. Замечательно. Маникюр отличный, а цена низкая. Рекомендую. Салон просторный, светлый, чистый. Вайфай летает, кофе из машины. Нормально. 5 баллов."}, {"rating": " ", "name": " ", "comment": "Здравствуйте, Анастасия. Благодарим Вас за отзыв. Будем рады увидеть Вас снова :)"}, {"rating": "5", "name": "Александра", "comment": "Мне понравилась мастер Алия, сделала все как я и хотела. Спасибо большое"}, {"rating": " ", "name": " ", "comment": "Здравствуйте, Александра. Нам очень приятно, что Вам у нас понравилось))) С радостью, встретим Вас снова :)"}, {"rating": "1", "name": "Татьяна", "comment": "Плюсы — симпатичный новый салон Минусы- делала маникюр с покрытием, но оказалось что в данном салоне практически никто не делает классический, только аппаратный. Ну да ладно, это не совсем страшно, все проходило хорошо все делали как надо. Самое интересное началось потом, к вечеру начали болеть ногти, пошла к другому мастеру, при диагностики ногтей оказалось что абсолютно неправильно выполнена работа, перепилена ногтевая пластина, гель лак растёкся по валикам так ещё и не досушен (с… – показать"}, {"rating": " ", "name": "CITY NAILS / Студии маникюра и красоты, Москва", "comment": "Дорогие наши девушки, в соответствии с указом Мэра Москвы наши студии будут закрыты с 28 марта по 5 апреля ⠀Но это не повод расстраиваться, сейчас лучшее время для себя, семьи и своего развития!⠀Ждём вас с 6 апреля Мы уже приготовили для вас нескольких интересных акций"}, {"rating": " ", "name": "CITY NAILS / Студии маникюра и красоты, Москва", "comment": "Ребята, у нас для вас две акции Успей записаться до 26.03!1⃣ Снятие бесплатно при маникюре или педикюре с покрытием Luxio 2⃣ Высокомолекулярный уход по типу волос ESTEL COUTURE LAB + стрижка кончиков по специальной цене 1790 рублей Всего за одну процедуру вы получаете здоровые, ухоженные волосыАкция проходит в студиях на : Белорусской Киевской Красных Воротах Чистых ПрудахАкция длится только до 26.03 Успей записаться! Запись в приложении City Nails, на сайте или по телефону +7 (499) 686-18-66"}, {"rating": " ", "name": "CITY NAILS / Студии маникюра и красоты, Москва", "comment": "Дорогие девушки, с праздником В честь 8 марта в нашем инстаграме мы запустили конкурс Дарим 3 сертификата: 2500р 1500р 1000р Все подробности по ссылке:"}], "images": [], "promos": [{"title": "Скидка тебе и подруге", "tag": "Акция «Приведи друга»", "card": "Постоянная акция"}, {"title": "🎉 Розыгрыш 4000 рублей! 🎉", "tag": "Специальная акция", "card": "Постоянная акция"}], "tags": ["Салоны красоты и СПА"], "witget": "no"}