{"title": "Похожие салоны красоты и спа поблизости", "rating": "3.6", "phone": "tel:+79772711443", "address": "Москва,  noindexЧечерский/noindex проезд,  66", "metro": ["Бунинская аллея 0.8 км", "Улица Горчакова 1.1 км"], "rayons": ["Округ ЮЗАО", "Район Бутово Южное"], "lonlat": ["37.524434999999997", "55.532716999999998"], "work_time": "Время работыежедневно: 10:00 - 22:00 ", "price": 0, "price_list": [], "stuff_list": [{"name": "Лилия Кобзарь ", "prof": "Маникюр, наращивание ногтей, педикюр", "img": "background-image: url('/images/placeholder_prof_170.png');"}, {"name": "Марина Салямова ", "prof": "Парикмахер", "img": "background-image: url('/images/placeholder_prof_170.png');"}], "site": "http://zoon.ru/redirect/?to=https%3A%2F%2Fvk.com%2Fdivine_beauty_studio_v_butovo&hash=573e725838c432e595ba35f77d0fc104&from=569e179b7389d5750f8b4568.6c38&ext_site=ext_vk&backurl=https%3A%2F%2Fzoon.ru%2Fmsk%2Fbeauty%2Fsalon_krasoty_divine_beauty_v_chechyorskom_proezde%2F", "its route": "No", "social_links": ["ВКонтакте http://zoon.ru/redirect/?to=https%3A%2F%2Fvk.com%2Fdivine_beauty_studio_v_butovo&hash=573e725838c432e595ba35f77d0fc104&from=569e179b7389d5750f8b4568.6c38&ext_site=ext_vk&backurl=https%3A%2F%2Fzoon.ru%2Fmsk%2Fbeauty%2Fsalon_krasoty_divine_beauty_v_chechyorskom_proezde%2F"], "reviews": [{"rating": " ", "name": "Евгения Симакина", "comment": "Вот такая у нас красота))"}, {"rating": " ", "name": "Divin Beauty Studio Бутово", "comment": "«Стиль создает легенду». Голосуй за мою работу в конкурсе от Panasonic!"}, {"rating": " ", "name": "Divin Beauty Studio Бутово", "comment": "Всех с праздником!"}, {"rating": " ", "name": "Divin Beauty Studio Бутово", "comment": "Кератиновое выпремление волосСтрижка в ПОДАРОК!!!!"}], "images": [], "promos": [], "tags": ["Салоны красоты и СПА", "Поиск", "Пол", "Специальность", "Любой стаж", "Детский"], "witget": "no"}