{"title": "Похожие салоны красоты и спа поблизости", "rating": " ", "phone": "tel:+79685460482", "address": "Москва,  noindexПерерва/noindex,  62 к2, 1 этаж", "metro": ["Братиславская 1.2 км", "Люблино 1.2 км"], "rayons": ["Округ ЮВАО", "Район Марьино"], "lonlat": ["37.766429000000002", "55.665010000000002"], "work_time": "Время работыежедневно: 10:00 - 22:00 ", "price": 0, "price_list": [], "stuff_list": [], "site": "http://zoon.ru/redirect/?to=https%3A%2F%2Fwww.instagram.com%2Fjust_best_nails&hash=ae03c0b56b5c1b540899f116ada1c7d4&from=5c00493ca24fd914013d90ed.d9c8&ext_site=ext_instagram&backurl=https%3A%2F%2Fzoon.ru%2Fmsk%2Fbeauty%2Fstudiya_manikyura_just_best_nails%2F", "its route": "No", "social_links": ["Instagram http://zoon.ru/redirect/?to=https%3A%2F%2Fwww.instagram.com%2Fjust_best_nails&hash=ae03c0b56b5c1b540899f116ada1c7d4&from=5c00493ca24fd914013d90ed.d9c8&ext_site=ext_instagram&backurl=https%3A%2F%2Fzoon.ru%2Fmsk%2Fbeauty%2Fstudiya_manikyura_just_best_nails%2F"], "reviews": [], "images": [], "promos": [], "tags": ["Салоны красоты и СПА"], "witget": "no"}