{"title": "Похожие салоны красоты и спа поблизости", "rating": "3.5", "phone": "tel:+74954790097", "address": "Москва,  Фрунзенская 3-я,  3, цокольный этаж", "metro": ["Фрунзенская 0.9 км", "Спортивная 1.1 км"], "rayons": ["Округ ЦАО", "Район Хамовники"], "lonlat": ["37.579771000000001", "55.718651000000001"], "work_time": "Время работыкруглосуточно24/7 ", "price": 0, "price_list": [], "stuff_list": [], "site": "http://zoon.ru/redirect/?to=https%3A%2F%2Fwww.instagram.com%2Fdorogoi_ya_skoro&hash=b391aaabf66d08f0d55eaa827d438ad1&from=5aa46e83a24fd974f057e6cc.6533&ext_site=ext_instagram&backurl=https%3A%2F%2Fzoon.ru%2Fmsk%2Fbeauty%2Fsalon_krasoty_dorogoj_ya_skoro%2F", "its route": "No", "social_links": ["Instagram http://zoon.ru/redirect/?to=https%3A%2F%2Fwww.instagram.com%2Fdorogoi_ya_skoro&hash=b391aaabf66d08f0d55eaa827d438ad1&from=5aa46e83a24fd974f057e6cc.6533&ext_site=ext_instagram&backurl=https%3A%2F%2Fzoon.ru%2Fmsk%2Fbeauty%2Fsalon_krasoty_dorogoj_ya_skoro%2F"], "reviews": [{"rating": "5", "name": " ", "comment": "Очень чётко, быстро и красиво! 5 из 5! Ксения, спасибо!"}], "images": [], "promos": [], "tags": ["Салоны красоты и СПА"], "witget": "no"}