{"title": "Акции студии красоты Карины Браун", "rating": "4.3", "phone": "tel:+79295308037", "address": "Московская область,  Химки,  Совхозная,  18", "metro": ["Ховрино 2.5 км"], "rayons": [], "lonlat": ["37.481988000000001", "55.900995999999999"], "work_time": "Время работыежедневно: 10:00 - 21:00 ", "price": "средняя", "price_list": [{"name": "Женская стрижка", "min-price": "200", "max-price": "—900"}, {"name": "Мужская стрижка", "min-price": "200", "max-price": "—500"}, {"name": "Наращивание ресниц", "min-price": "0", "max-price": "—4500"}, {"name": "Окрашивание волос", "min-price": "1000", "max-price": "—8000"}, {"name": "Детская стрижка", "min-price": " ≈ 400", "max-price": " "}], "stuff_list": [{"name": "Карина  Аваговна Асатрян  ", "prof": "Лэшмейкер, наращивание ресниц, перманентный макияж", "img": "background-image: url(\"https://p1.zoon.ru/preview/qelVLH3UPlWjaGvggMcU6w/130x170x90/1/7/7/5df747126505383fed5c1416_5df7484239c86.jpg\");"}, {"name": "Нона  Аваговна Асатрян ", "prof": "Маникюр, мастер ногтевого сервиса, педикюр", "img": "background-image: url(\"https://p1.zoon.ru/preview/xw_BYHx_R7H-MuzJkpqxVg/130x170x90/1/0/d/5daef4dabfd56125a60ac768_5daef5262e539.jpg\");"}], "site": "http://kariny-braun-salon.ru?token=20200427015142rvNs", "its route": "No", "social_links": ["kariny-braun-salon.ru http://kariny-braun-salon.ru?token=20200427015142rvNs"], "reviews": [{"rating": "5", "name": "Артём", "comment": "Благодарю за профессиональную работу и качественное обслуживание. Сотрудники все доброжелательны, а стрижка на высшем уровне!"}, {"rating": " ", "name": " ", "comment": "Добрый день, уважаемый Артём. Примите нашу искреннюю благодарность за отзыв, нам ценно ваше мнение о нашей работе. Нам очень приятно, что вы столь высоко оцениваете качество наших услуг. Мы постараемся и в дальнейшем радовать вас безупречным уровнем сервиса. Надеемся, что вы воспользуетесь и другими предложениями из нашего широкого ассортимента. Желаем вам крепкого здоровья и всего наилучшего. Всегда ваши, администрация студии красоты Карины Браун."}], "images": [], "promos": [{"title": "Коррекция и окрашивание бровей в подарок", "tag": "Специальная акция", "card": "Осталось 2 дня, до 29 апреля 2020"}, {"title": "Маникюр со скидкой! Только сегодня", "tag": "Специальная акция", "card": "Остался 1 день, до 28 апреля 2020"}, {"title": "-20% в день рождения", "tag": "Акция на День рождения", "card": "Осталось 2 дня, до 29 апреля 2020"}, {"title": "Приведи друга и получи 10% скидку", "tag": "Акция «Приведи друга»", "card": "Остался 1 день, до 28 апреля 2020"}], "tags": ["Салоны красоты и СПА", "Поиск", "Пол", "Специальность", "Любой стаж", "Детский"], "witget": "no"}