{"title": "Эконом-парикмахерская на метро ВДНХ", "rating": "4.7", "phone": "tel:+74956151164", "address": "Москва, Звёздный бульвар, 12 к1, цокольный этаж", "metro": ["ВДНХ 0.7 км", "Алексеевская 1 км"], "rayons": ["Округ СВАО", "Район Останкинский"], "lonlat": ["37.632494999999999", "55.816898000000002"], "work_time": "Время работыежедневно: 09:00 - 21:00 ", "price": 0, "price_list": [], "stuff_list": [], "site": "http://zoon.ru/redirect/?to=https%3A%2F%2Fwww.msk-strijka.com%2F&hash=96b9ee8496d4d604cd73aa31417b5ad3&from=58e18a1140c0886f708baed7.3d77&ext_site=ext_site&backurl=https%3A%2F%2Fzoon.ru%2Fmsk%2Fbeauty%2Fekonom-parikmaherskaya_na_metro_vdnh%2Freviews%2F", "its route": "No", "social_links": ["www.msk-strijka.com/ http://zoon.ru/redirect/?to=https%3A%2F%2Fwww.msk-strijka.com%2F&hash=96b9ee8496d4d604cd73aa31417b5ad3&from=58e18a1140c0886f708baed7.3d77&ext_site=ext_site&backurl=https%3A%2F%2Fzoon.ru%2Fmsk%2Fbeauty%2Fekonom-parikmaherskaya_na_metro_vdnh%2Freviews%2F", "ВКонтакте http://zoon.ru/redirect/?to=https%3A%2F%2Fvk.com%2Fclub138571375&hash=25dc18da0aca432141502e1937da3f5f&from=58e18a1140c0886f708baed7.3d77&ext_site=ext_vk&backurl=https%3A%2F%2Fzoon.ru%2Fmsk%2Fbeauty%2Fekonom-parikmaherskaya_na_metro_vdnh%2Freviews%2F", "Instagram http://zoon.ru/redirect/?to=https%3A%2F%2Fwww.instagram.com%2Fmskstrijka&hash=d4d22e52f4da367c912d14acced3d105&from=58e18a1140c0886f708baed7.3d77&ext_site=ext_instagram&backurl=https%3A%2F%2Fzoon.ru%2Fmsk%2Fbeauty%2Fekonom-parikmaherskaya_na_metro_vdnh%2Freviews%2F"], "reviews": [{"rating": " ", "name": "Анюта Лобышева", "comment": "Сайт не открывает! Где Ваш номер найти?"}, {"rating": " ", "name": "Марьяна Елисеева", "comment": "Почему нас выбрали ваши конкуренты?theBEAUTY новая площадка, признанная одной из самых эффективных в рекламе за 2019 год. Наши преимущества:• Простой и понятный интерфейс;• Низкая цена — высокое качество;• Известный бренды уже выбрали нас;• Интернет реклама не теряет своей актуальности;• Бесплатный пробный период по промокоду «F777». Познакомимся ближе? Переходи на () и читай закрепленную статью ()."}, {"rating": " ", "name": "Елена Махова", "comment": "Здравствуйте, можно у вас приобрести подарочный сертификат? Каким номиналом?"}, {"rating": " ", "name": "Мира Ханипова", "comment": "ПРОШУ СОВЕТ! Всем Привет!Недавно красила волосы в зелёный цвет Теперь хочу в розовый, но зелёный не смывается, точнее сложно смывается. Что посоветуете??? Как смыть зелёный цвет? Спасибо заранее всем за ответ!"}, {"rating": " ", "name": "Олеся Максимова", "comment": "Мира, спасибо Да, для меня красота как образ жизни!"}, {"rating": " ", "name": "Мира Ханипова", "comment": "Олеся, У вас очень интересная страничка, тоже интересуетесь в сфере красоты?"}, {"rating": " ", "name": "Мира Ханипова", "comment": "Алла, тоже подумала)"}, {"rating": " ", "name": "Мира Ханипова", "comment": "Олеся, спасибо"}, {"rating": " ", "name": "Алла Насырова", "comment": "Привет1 Наверное лучше обратиться к профессионалам и они уж точно превратят цвет волос в тот, который ты желаешь)))"}, {"rating": " ", "name": "Олеся Максимова", "comment": "Думаю, что надо вернуться к своему цвету, а потом уже краситься в розовый."}, {"rating": " ", "name": "Сеть парикмахерских", "comment": "Всего 700 руб.!!! Маникюр с покрытием SHELLAC всего 700 руб.!!!"}, {"rating": " ", "name": "Сеть парикмахерских", "comment": "ЭКОНОМ ПАРИКМАХЕРСКАЯ СТРИЖКА……………………………………………………...............................…………. ОТ 200 РУБ. ОКРАШИВАНИЕ…………………………………………...............................…………. ОТ 300 РУБ. МЕЛИРОВАНИЕ……………………………………..............................……………..… ОТ 350 РУБ. УКЛАДКА……………………………………………………................................…………. ОТ 150 РУБ. МАНИКЮР…………………………………………………………..................................… ОТ 200 РУБ. МАНИКЮР + ПОКРЫТИЕ SHELLAC……………………..........................……….. 700 РУБ. ПЕДИКЮР……………………………………………………………................................… ОТ 550… — Читать дальше РУБ. НАРАЩИВАНИЕ НОГТЕЙ…………………………………..............................… ОТ 1100 РУБ. ПЕНСИОНЕРАС СКИДКА ДО 13:00 МУЖСКАЯ СТРИЖКА 150 РУБ. ЖЕНСКАЯ СТРИЖКА 180 РУБ. Г. МОСКВА УЛ. АКАДЕМИКА КОРОЛЕВА Д.7 К.1 РАБОТАЕМ С 09:00 ДО 21:00 ТЕЛ.: +7 (495) 615-11-64 Г. МОСКВА ЗВЕЗДНЫЙ БУЛЬВАР Д.12 К.1 РАБОТАЕМ С 09:00 ДО 21:00 ТЕЛ.: +7 (495) 615-11-64 ТЕЛ.:+7 (495) 615-11-64 "}, {"rating": " ", "name": "Сеть парикмахерских", "comment": "Марина Васильева (14.03.2017):Наращивание ресниц — пореснично 1500 руб. Наращивание ресниц — пучками 1000 руб. Наращивание ресниц — уголки 600 руб. Ламинирование ресниц 1500 руб. Снятие ресниц 300 руб."}], "images": ["https://p0.zoon.ru/preview/12J8b5PSnSM9xDnmmxUwOw/1200x1200x85/1/8/d/original_58e18a1140c0886f708baed8_5d55b59516c5f.jpg", "https://p0.zoon.ru/preview/H4WgyTZ3fx9sHyFWMtJT2Q/1200x1200x85/1/8/2/original_58e18a1140c0886f708baed8_5d55b5956f917.jpg", "https://p1.zoon.ru/preview/-3TzBhPA9oiaY6ymENxxxw/1200x1200x85/1/8/4/original_58e18a1140c0886f708baed8_5d55b595e002d.jpg", "https://p0.zoon.ru/preview/i9VDSoNl2PCKMKysMRzlSw/1200x1200x85/1/3/b/original_58e18a1140c0886f708baed8_5d55b596482cf.jpg", "https://p1.zoon.ru/preview/YscdrVEKKyhZVDgkJDk5Mw/1200x1200x85/1/e/d/original_58e18a1140c0886f708baed8_5d55b596ab6dc.jpg", "https://p0.zoon.ru/preview/8EcJ2COhupqhA0LnECEVOQ/1200x1200x85/1/3/8/original_58e18a1140c0886f708baed8_5d55b59787200.jpg", "https://p0.zoon.ru/preview/d2A1eOApKJuCXaG4P8XU6g/1200x1200x85/1/c/8/original_58e18a1140c0886f708baed8_5d55b598750c9.jpg", "https://p0.zoon.ru/preview/P12zxVCCLkKT0q6jgh2rOQ/1200x1200x85/1/6/1/original_58e18a1140c0886f708baed8_5d55b59933420.jpg", "https://p1.zoon.ru/preview/RH-ZB9C9qP7cwf3FnOgIBQ/1200x1200x85/1/3/9/original_58e18a1140c0886f708baed8_5d55b59994427.jpg", "https://p0.zoon.ru/preview/q2M-yN7iFzA5qdPUMRJTYg/1200x1200x85/1/4/8/original_58e18a1140c0886f708baed8_5d55b59a2073f.jpg", "https://p2.zoon.ru/preview/bfjYU0crMoBBXw0g6acPlQ/1200x1200x85/1/1/c/original_58e18a1140c0886f708baed8_5d55b59a8117f.jpg", "https://p1.zoon.ru/preview/nvE7kBH6kzm4-urmaGeDYQ/1200x1200x85/1/4/a/original_58e18a1140c0886f708baed8_5d55b59b33fd7.jpg"], "promos": [], "tags": ["Салоны красоты и СПА"], "witget": "no"}