{"title": "28 фотографий из Instagram", "rating": "1", "phone": "tel:+74752435365", "address": "Тамбов,  улица noindexСоветская/noindex,  56, 1 этаж", "lonlat": ["41.463354000000002", "52.710748000000002"], "work_time": "Время работыежедневно: 10:00 - 20:00 ", "price": 0, "price_list": [], "stuff_list": [], "site": "http://zoon.ru/redirect/?to=http%3A%2F%2F%E2%80%9C%D1%82%D0%BE%D1%87%D0%BA%D0%B0+%D0%B7%D0%B4%D0%BE%D1%80%D0%BE%D0%B2%D1%8C%D1%8F%E2%80%9D+-+%D1%8D%D1%82%D0%BE+%D0%BF%D0%B5%D1%80%D0%B2%D0%BE%D0%B5+%D0%BC%D0%B5%D1%81%D1%82%D0%BE+%D1%82%D0%B0%D0%BC%D0%B1%D0%BE%D0%B2%D0%B0%2C+%D0%B3%D0%B4%D0%B5+%D0%B2+%D0%BE%D0%B4%D0%BD%D0%BE%D0%BC+%D0%BC%D0%B5%D1%81%D1%82%D0%B5+%D1%81%D0%BE%D0%B1%D1%80%D0%B0%D0%BD%D0%BE+%D0%B2%D1%81%D1%91%2C+%D1%87%D1%82%D0%BE+%D0%BD%D1%83%D0%B6%D0%BD%D0%BE+%D0%B4%D0%BB%D1%8F+%D0%B7%D0%B4%D0%BE%D1%80%D0%BE%D0%B2%D1%8C%D1%8F.++-+%D1%81%D0%BE%D0%BB%D1%8F%D0%BD%D1%8B%D0%B5+%D0%BF%D0%B5%D1%89%D0%B5%D1%80%D1%8B+-+%D0%BC%D0%B0%D0%B3%D0%B0%D0%B7%D0%B8%D0%BD%D1%8B+%D0%BF%D1%80%D0%B0%D0%B2%D0%B8%D0%BB%D1%8C%D0%BD%D1%8B%D1%85+%D0%BF%D1%80%D0%BE%D0%B4%D1%83%D0%BA%D1%82%D0%BE%D0%B2+-+%D0%BC%D0%B0%D1%81%D1%81%D0%B0%D0%B6%D0%B8+-+%D1%8D%D0%BA%D0%BE-%D0%B1%D0%B0%D1%80+-+%D0%BE%D0%B1%D1%80%D0%B0%D0%B7%D0%BE%D0%B2%D0%B0%D1%82%D0%B5%D0%BB%D1%8C%D0%BD%D0%BE%D0%B5+%D0%BF%D1%80%D0%BE%D1%81%D1%82%D1%80%D0%B0%D0%BD%D1%81%D1%82%D0%B2%D0%BE++__________________________++%D1%87%D0%B5%D0%BC+%D0%BC%D1%8B+%D0%BF%D0%BE%D0%BB%D0%B5%D0%B7%D0%BD%D1%8B%3A++-+%D0%BF%D0%BE%D0%BC%D0%BE%D0%B3%D0%B0%D0%B5%D0%BC+%D1%83%D0%BA%D1%80%D0%B5%D0%BF%D0%B8%D1%82%D1%8C+%D0%B8%D0%BC%D0%BC%D1%83%D0%BD%D0%B8%D1%82%D0%B5%D1%82+%D0%B8+%D0%B2%D1%8B%D0%BB%D0%B5%D1%87%D0%B8%D1%82%D1%8C+%D0%B7%D0%B0%D0%B1%D0%BE%D0%BB%D0%B5%D0%B2%D0%B0%D0%BD%D0%B8%D1%8F+%D0%BB%D0%BE%D1%80-%D0%BE%D1%80%D0%B3%D0%B0%D0%BD%D0%BE%D0%B2+%D0%B1%D0%B5%D0%B7+%D0%BB%D0%B5%D0%BA%D0%B0%D1%80%D1%81%D1%82%D0%B2.+%D0%BE%D1%82%D0%B7%D1%8B%D0%B2%D1%8B+%D0%BE+%D1%81%D0%BE%D0%BB%D1%8F%D0%BD%D0%BE%D0%B9+%D0%BF%D0%B5%D1%89%D0%B5%D1%80%D0%B5%3A+https%2F%2Fvk.com%2Ftopic-70002386_30205374++-+%D1%80%D0%B0%D1%81%D1%81%D0%BB%D0%B0%D0%B1%D0%BB%D1%8F%D0%B5%D0%BC+%D1%82%D0%B5%D0%BB%D0%BE+%D0%B8+%D1%83%D0%BC%2C+%D0%BF%D1%80%D0%BE%D0%B2%D0%BE%D0%B4%D0%B8%D0%BC+%D0%BC%D0%B0%D1%81%D1%81%D0%B0%D0%B6%D0%B8+%D0%B8+%D0%B0%D1%8E%D1%80%D0%B2%D0%B5%D0%B4%D0%B8%D1%87%D0%B5%D1%81%D0%BA%D0%B8%D0%B5+%D0%BF%D1%80%D0%BE%D1%86%D0%B5%D0%B4%D1%83%D1%80%D1%8B+%D0%B2+spa-%D1%86%D0%B5%D0%BD%D1%82%D1%80%D0%B5+%22%D0%BF%D0%B0%D1%80%D0%B2%D0%B0%D1%82%D0%B8%22%3A+vk.com%2Fparvati_sp&hash=d1624aff593dbdb0178c69be757235dd&from=5a3c6105a24fd925a90cbac6.166e&ext_site=ext_site&backurl=https%3A%2F%2Ftambov.zoon.ru%2Fbeauty%2Fsolyanaya_peschera_tochka_zdorovya_v_leninskom_rajone%2F", "reviews": [{"rating": " ", "name": "Соляная пещера | Тамбов | Точка Здоровья", "comment": "Друзья, сегодня «Точка Здоровья» открыта до 18 часов! Завтра, 13 марта, у нас выходной. Обещаем оборудовать соляную пещеру для вас комфортнее и удобнее. Просим прощения за временные неудобства!До встречи в субботу!"}, {"rating": " ", "name": "Соляная пещера | Тамбов | Точка Здоровья", "comment": "Каблуки: «за» и «против» с точки зрения анатомии || Лекция в «Точке здоровья»В следующее воскресенье, 22 марта, в «Точке здоровья» пройдет познавательная лекция о биомеханике тела при ношении обуви на высоком каблуке. О чем мы поговорим? влияние обуви с высоким каблуком на коленные суставы; а также на поясничный отдел позвоночника; связь между основными деформациями начиная со стоп и заканчивая шеей; механизм деформации таза; влияние обуви на высоком каблуке на работу органов малого таза.Бонус: практические упражнения из йоги,… — Читать дальше которые помогут избавиться от последствий ношения высоких каблуков. 22 марта в 16:00. Лекцию проведет Дарья Трюфилькина — инструктор по аэройоге для взрослых и детей, ведущая занятий «Здоровая спина», энерготерапевт. Стоимость: 350 рублей. Запись по телефону: 435—365, либо личным сообщением Дарье.Приходите! Будет очень интересно! "}, {"rating": " ", "name": "Соляная пещера | Тамбов | Точка Здоровья", "comment": "Друзья, сегодня «Точка Здоровья» открыта до 17 часов!Вы ещё успеваете к нам за солевой лампой или подарочным сертификатом. Завтра, 9 марта, у нас выходной. До встречи во вторник!"}], "images": ["https://p1.zoon.ru/preview/zXdKzJykJWiIe6YT9kvw1g/1200x1200x85/1/1/c/original_5a3c6105a24fd925a90cbac7_5e5dd5682fcfb.jpg", "https://p2.zoon.ru/preview/rWSuHzZzLOwsCUId6ABggw/1200x1200x85/1/f/8/original_5a3c6105a24fd925a90cbac7_5e5dd56bdb1df.jpg", "https://p2.zoon.ru/preview/QyoDpJDBs1YB43LcgrPmfg/1200x1200x85/1/2/d/original_5a3c6105a24fd925a90cbac7_5e5dd5731e54d.jpg", "https://p1.zoon.ru/preview/7bmixfj3rcP0L-5uLB4-rQ/1200x1200x85/1/c/b/original_5a3c6105a24fd925a90cbac7_5e5dd58289405.jpg", "https://p2.zoon.ru/preview/pShsI1eIdNYvwpp6FQLd6A/1200x1200x85/1/5/7/original_5a3c6105a24fd925a90cbac7_5e5dd59225734.jpg", "https://p2.zoon.ru/preview/hpCvYSjVCX4PtVLT1MgpNQ/1200x1200x85/1/e/3/original_5a3c6105a24fd925a90cbac7_5e5dd59f63afa.jpg", "https://p2.zoon.ru/preview/YE0qoaROutNqiqnCAv1REg/1200x1200x85/1/9/a/original_5a3c6105a24fd925a90cbac7_5e5dd5a3b2ed9.jpg", "https://p1.zoon.ru/preview/BNpyLskd7vDPtxTgjYMwNw/1200x1200x85/1/e/f/original_5a3c6105a24fd925a90cbac7_5e5dd5a78913e.jpg", "https://p2.zoon.ru/preview/1grLBIAX_p5kDp7BBMHMug/1200x1200x85/1/9/e/original_5a3c6105a24fd925a90cbac7_5e5dd5aa3cce5.jpg", "https://p2.zoon.ru/preview/zYDr3hJBkNbwRBu6tOsGUg/1200x1200x85/1/d/2/original_5a3c6105a24fd925a90cbac7_5e5dd5b02ee5d.jpg", "https://p1.zoon.ru/preview/1uZQWIzUf-lgEMdqiKpdXA/1200x1200x85/1/e/d/original_5a3c6105a24fd925a90cbac7_5e5dd5b45e40c.jpg", "https://p1.zoon.ru/preview/l0DmGKN2owDQ6-dap4dglA/1200x1200x85/1/7/6/original_5a3c6105a24fd925a90cbac7_5e5dd5bb66578.jpg"], "promos": [], "tags": ["Салоны красоты и СПА"], "witget": "no"}