{"title": "Студия красоты Взгляд в Южном районе", "rating": "5", "phone": "tel:+79282800609", "address": "Новороссийск, Дзержинского проспект, 232, 24 офис; 2 этаж", "lonlat": ["37.780290000000001", "44.673279999999998"], "work_time": "Время работыежедневно: 10:00 - 20:00 ", "price": 0, "price_list": [], "stuff_list": [], "site": "http://zoon.ru/redirect/?to=https%3A%2F%2Fvk.com%2Fk.rabbota&hash=c688636220c27bb6d2a9d8a3f7c83262&from=57e0b45040c088833c8c3f09.0bf0&ext_site=ext_vk&backurl=https%3A%2F%2Fnovorossiysk.zoon.ru%2Fbeauty%2Fstudiya_krasoty_vzglyad_v_yuzhnom_rajone%2Freviews%2F", "reviews": [{"rating": " ", "name": "Анонимный пользователь", "comment": "Сколько времени держатся нарощенные ресницы?"}, {"rating": " ", "name": "Катя Масянина", "comment": "Девочки всем советую. Мастер шикарный,бережно и аккуратно относиться к работе. Все на высшем уровне)"}, {"rating": " ", "name": "Катя Масянина", "comment": "Катерина,)))за правду спасибо не говорят) жди меня завтра)"}, {"rating": " ", "name": "Катерина Рабочая", "comment": "Спасибо моя красавица!)))"}, {"rating": " ", "name": "Катерина Рабочая", "comment": "Зима совсем близко!))"}, {"rating": " ", "name": "Катерина Рабочая", "comment": "Покрытие гелем 800Записываемся скорей!))"}, {"rating": " ", "name": "Катерина Щербакова", "comment": "Внимание!!)) Теперь вы можете записаться ко мне Онлайн!Быстро! Очень легко! И ОЧЕНЬ просто!))Просто зайдите в приложение Или скачайте его себе на телефон! Ссылки для скачивания: iPhone — Android — Онлайн-запись является равнозначной записи по телефону и не требует подтверждения!"}, {"rating": " ", "name": "Катерина Рабочая", "comment": "Еще ярче!))"}, {"rating": " ", "name": "Катерина Рабочая", "comment": "Наращивание ресниц 2d и любая длина 1500руб"}, {"rating": " ", "name": "Катерина Рабочая", "comment": "Наращивание ногтей!) 1500Коррекция 1000Записываемся!)"}, {"rating": " ", "name": "Анастасия Мартынюк", "comment": "Какая стоимость наращивание ногтей? И есть ли запись на завтра?"}, {"rating": " ", "name": "Анастасия Кошелева", "comment": "Девочки, добрый день! Кому нужны материалы фирмы Коди? Отзовитесь, срочно!"}, {"rating": " ", "name": "Катерина Щербакова", "comment": "Записывается не стесняемся!))))"}, {"rating": " ", "name": "Ирина Ермантович", "comment": "Уважаемые администраторы! Возможно Вашим подписчикам будет интересна информация о КУРСАХ АРОЧНОГО МОДЕЛИРОВАНИЯ ногтей в Анапе. Подробности в группе"}, {"rating": " ", "name": "Катерина Рабочая", "comment": "Девочки ‍ ️ ищем модель на наращивание ресничек на 19.10(суббота) в 14:00 (объем 2d) Оплата 500р (только за материал) .За красивыми ресничками ждем вас в нашей студии красоты «Взгляд» . +7 (928) 280-06-09"}, {"rating": " ", "name": "Катерина Рабочая", "comment": "Внимание!! ‍ ️ ищем моделей на наращивание ресничек (объем 2d) Оплата 500р (только за материал) .За красивыми ресничками ждем вас в нашей студии красоты «Взгляд» . +7 (928) 280-06-09"}, {"rating": " ", "name": "Катерина Рабочая", "comment": "Внимание!!! ‍ ️ На 26 апреля время 12:30 ищем МОДЕЛЕЙ на классическое и 1,5d наращивание ресниц к опытному мастеру студии.Оплата 500 руб(только за материал) .Хочешь красивые реснички, мы ждем Вас в студии красоты «Взгляд» . +7 (928) 280-06-09."}], "images": ["https://p1.zoon.ru/preview/LkUJgNzj9LhEj86SV9HPIQ/1200x1200x85/1/b/3/original_57e0b45040c088833c8c3f0a_5e6d877bdb966.jpg", "https://p0.zoon.ru/preview/7kz93MI8-x6jiS1_CqSgQw/1200x1200x85/1/f/4/original_57e0b45040c088833c8c3f0a_5e6d8788302ef.jpg", "https://p0.zoon.ru/preview/tAUwxBlVlAsO14vaNVcZgg/1200x1200x85/1/f/1/original_57e0b45040c088833c8c3f0a_5e6d878fe6a59.jpg", "https://p1.zoon.ru/preview/aez2U7MJKZGCDqxHIjrKhw/1200x1200x85/1/1/9/original_57e0b45040c088833c8c3f0a_5e6d8792b659a.jpg", "https://p0.zoon.ru/preview/kh5nWiIKN5ODhsqwOXAwMA/1200x1200x85/1/7/b/original_57e0b45040c088833c8c3f0a_5e6d87994c214.jpg", "https://p1.zoon.ru/preview/ncDK160HTtg6lCm7MpXC3Q/961x1200x85/1/5/e/original_57e0b45040c088833c8c3f0a_5e6d87a52e4fb.jpg", "https://p1.zoon.ru/preview/VCIy5j1hldvTIwDTE6O_qw/1200x1200x85/1/4/6/original_57e0b45040c088833c8c3f0a_5e6d87ac2e2d7.jpg", "https://p2.zoon.ru/preview/Quf5cPS4h2wn77ahJiuVtA/1200x1200x85/1/2/4/original_57e0b45040c088833c8c3f0a_5e6d87b4530d9.jpg", "https://p2.zoon.ru/preview/tUkP8w_oC-OG3b_NoAL4og/1200x1200x85/1/3/4/original_57e0b45040c088833c8c3f0a_5e6d87b5dc9f1.jpg", "https://p0.zoon.ru/preview/YmTok1qONTXRSOoPZ6441g/1200x1200x85/1/c/f/original_57e0b45040c088833c8c3f0a_5e6d87bad654f.jpg", "https://p0.zoon.ru/preview/8BqaK2P22w9u7dSYR9b21g/1200x1200x85/1/0/0/original_57e0b45040c088833c8c3f0a_5e6d87bd9adf5.jpg", "https://p1.zoon.ru/preview/RoEDBm-Koin-iiuvMNJ0EA/1200x1200x85/1/6/0/original_57e0b45040c088833c8c3f0a_5e6d87bfa7111.jpg"], "promos": [], "tags": ["Салоны красоты и СПА"], "witget": "no"}