{"title": "Акции нейл-бара НогтеТочка в ТЦ Никольский", "rating": "4.5", "phone": "tel:+79109830195", "address": "Иваново,  проспект noindexЛенина/noindex,  57А", "lonlat": ["40.968395999999998", "57.018056000000001"], "work_time": "Время работыежедневно: 09:00 - 20:00 ", "price": 0, "price_list": [{"name": "Коррекция бровей", "min-price": " ≈ 150", "max-price": " "}], "stuff_list": [{"name": "Валентина Маулиева ", "prof": "Бровист, дизайн ногтей, коррекция бровей, маникюр, мастер ногтевого сервиса, наращивание ногтей", "img": "background-image: url(\"https://p2.zoon.ru/preview/U9zBSBrp2Vbt80MBPcKoeg/130x170x90/1/5/8/5c9fbff0f5a482ec4c45b8a4_5de2cedd2bfe8.jpg\");"}, {"name": "Анастасия Гарелина ", "prof": "Мастер ногтевого сервиса", "img": "background-image: url(\"https://p0.zoon.ru/preview/N4r_A7TgiaVXqllaN_vlqQ/130x170x90/1/1/0/5d34d2e9ffec4b0c5a1a7d57_5e26181791d78.jpg\");"}], "site": "http://zoon.ru/redirect/?to=https%3A%2F%2Fapp.arnica.pro%2Fbooking%2Fbooking%3Forgid%3D49978&hash=28e76bd8bc54a897aaa50794d44c6a70&from=5c9302d1e98b801f205a930f.caf1&ext_site=ext_site&backurl=https%3A%2F%2Fivanovo.zoon.ru%2Fbeauty%2Fnejl-bar_nogtetochka_v_tts_nikolskij%2F", "reviews": [{"rating": " ", "name": "Нейл бар \"НогтеТочка\"", "comment": "Опубликуйте в Сториз до 16 февраля фото маникюра из нашего нейл бара, отметьте нас, и получите скидку 10%. И скидку на следующее посещение 30%."}, {"rating": " ", "name": "Нейл бар \"НогтеТочка\"", "comment": "Online запись"}, {"rating": " ", "name": "Нейл бар \"НогтеТочка\"", "comment": "15 октября нам 2 года! К нашему Дню рождения С 14 по 20 октября Дарим специальную цену на маникюр с покрытием гель-лак! Успейте записаться! +7 (910) 983-01-95***----------------***-—"}], "images": ["https://p1.zoon.ru/preview/JtTTzBcUJGInE_80j96miA/800x600x85/1/8/f/original_5c9302d1e98b801f205a9313_5dfbe2243daf3.jpg"], "promos": [{"title": "Скидка за подписку в ig", "tag": "Специальная акция", "card": "Постоянная акция"}], "tags": ["Салоны красоты и СПА", "Поиск", "Пол", "Специальность", "Любой стаж", "Детский"], "witget": "no"}