{"title": "Похожие салоны красоты и спа поблизости", "rating": "2", "phone": "tel:+74862633370", "address": "Орёл,  noindexКомсомольская/noindex,  66, 301 офис; 3 этаж", "lonlat": ["36.062682000000002", "52.954543000000001"], "work_time": "Время работыПн-Пт, Вс: 09:00—21:00по предварительной записи: пн-пт, вс ", "price": "очень высокая", "price_list": [], "stuff_list": [], "site": "http://zoon.ru/redirect/?to=http%3A%2F%2Forelkolibri.ru&hash=6a1340668089345ccbad860023319b92&from=5936d71f70fc03074e38df5b.6d95&ext_site=ext_site&backurl=https%3A%2F%2Forel.zoon.ru%2Fbeauty%2Fstudiya_nogtevogo_servisa_kolibri%2F", "reviews": [{"rating": "1", "name": "Ирина", "comment": "Записаться возможно только за месяц. При уточнении свободных мастеров столкнулась с хамским поведением и общением, желания там появляться не возникло"}, {"rating": " ", "name": "Студия \"Колибри\": маникюр, педикюр. г. Орел.", "comment": "Комбинированный маникюр + гелевая коррекция. Дизайн вручную."}, {"rating": " ", "name": "Студия \"Колибри\": маникюр, педикюр. г. Орел.", "comment": "Комбинированный маникюр + гель-лак. Дизайн акварелью."}, {"rating": " ", "name": "Студия \"Колибри\": маникюр, педикюр. г. Орел.", "comment": "Комбинированный маникюр + гель-лак. Дизайн вручную."}], "images": [], "promos": [], "tags": ["Салоны красоты и СПА"], "witget": "no"}